{
  "generated": "2026-06-29T05:02:20.755067+00:00",
  "ts": 1782709340,
  "market": [
    {
      "headline": "$4 billion gone. Spot bitcoin ETFs are on track for their worst month on record",
      "take": "Spot bitcoin ETFs tracking worst month on record with $4 billion outflows",
      "source": "coindesk",
      "link": "https://www.coindesk.com/markets/2026/06/29/usd4-billion-gone-spot-bitcoin-etfs-are-on-track-for-their-worst-month-on-record"
    },
    {
      "headline": "China\u2019s M2 money supply reaches record 240% of GDP",
      "take": "China's M2 money supply reaches record 240 percent of GDP, signaling monetary expansion",
      "source": "cryptobriefing",
      "link": "https://cryptobriefing.com/china-m2-money-supply-record-240-percent-gdp/"
    },
    {
      "headline": "Copper falls as Federal Reserve\u2019s hawkish stance pressures prices",
      "take": "Copper prices fall as Federal Reserve maintains hawkish monetary policy stance",
      "source": "cryptobriefing",
      "link": "https://cryptobriefing.com/copper-falls-fed-hawkish-stance-pressures-prices/"
    },
    {
      "headline": "Tech stocks surpass 50% of S&P 500 index for first time",
      "take": "Tech stocks exceed fifty percent of S&P 500 index weighting for first time",
      "source": "cryptobriefing",
      "link": "https://cryptobriefing.com/tech-stocks-surpass-50-percent-sp500/"
    }
  ],
  "business": [
    {
      "headline": "SharpLink buys $62M worth of Ethereum after eight-month pause",
      "take": "SharpLink purchases $62 million worth of Ethereum after eight-month hiatus",
      "source": "cryptobriefing",
      "link": "https://cryptobriefing.com/sharplink-buys-62m-ethereum-pause/"
    },
    {
      "headline": "Dubai\u2019s VARA licenses 50th crypto firm as market expands",
      "take": "Dubai's VARA licenses fiftieth cryptocurrency firm as regional market expands",
      "source": "cryptobriefing",
      "link": "https://cryptobriefing.com/dubai-vara-licenses-50th-crypto-firm/"
    },
    {
      "headline": "South Korea\u2019s Kiwoom Securities to acquire stake in Bithumb crypto exchange: report",
      "take": "South Korea's Kiwoom Securities to acquire stake in Bithumb crypto exchange",
      "source": "theblock",
      "link": "https://www.theblock.co/post/406470/kiwoom-securities-bithumb?utm_source=rss&utm_medium=rss"
    },
    {
      "headline": "American Express hires VP of stablecoin and blockchain partnerships",
      "take": "American Express hires VP of stablecoin and blockchain partnerships",
      "source": "cryptobriefing",
      "link": "https://cryptobriefing.com/american-express-stablecoin-blockchain-vp/"
    }
  ],
  "security": [],
  "policy": [
    {
      "headline": "BIS warns stablecoins risk fragmenting global financial system",
      "take": "BIS warns stablecoins risk fragmenting global financial system in annual report",
      "source": "cointelegraph_regulation",
      "link": "https://cointelegraph.com/news/bis-warns-stablecoins-risk-fragmenting-global-financial-system?utm_source=rss_feed&utm_medium=rss_tag_regulation&utm_campaign=rss_partner_inbound"
    }
  ]
}